e2e_testing_framework/__init__.py
e2e_testing_framework/basemanager.py
e2e_testing_framework/exception.py
e2e_testing_framework/manager.py
e2e_testing_framework-0.1.dist-info/LICENSE.txt
e2e_testing_framework-0.1.dist-info/METADATA
e2e_testing_framework-0.1.dist-info/WHEEL
e2e_testing_framework-0.1.dist-info/top_level.txt
e2e_testing_framework-0.1.dist-info/RECORD
