Metadata-Version: 2.1
Name: e2e_testing_framework
Version: 0.1
Summary: testing platform for unittest test cases
Author: Neethukrishnan P
License: MIT
License-File: LICENSE.txt
Requires-Dist: requests
Requires-Dist: fastapi
Requires-Dist: pytest
